django_selenium_test/__init__.py
django_selenium_test/core.py
django_selenium_test/integration.py
django_selenium_test/settings.py
tests/__init__.py
tests/forms.py
tests/manage.py
tests/settings.py
tests/urls.py
tests/views.py
tests/tests/__init__.py
tests/tests/test_01_core.py
tests/tests/test_02_integration.py
tests/tests/test_03_user_autologin.py
django_selenium_test-2.0.0.dist-info/LICENSE.txt
django_selenium_test-2.0.0.dist-info/METADATA
django_selenium_test-2.0.0.dist-info/WHEEL
django_selenium_test-2.0.0.dist-info/top_level.txt
django_selenium_test-2.0.0.dist-info/RECORD
