Metadata-Version: 2.1
Name: django-selenium-test
Version: 2.0.0
Summary: Write clean Selenium tests in Django
Home-page: https://github.com/tkw1536/django_selenium_test
Author: Tom Wiesing
Author-email: tkw01536@gmail.com
License: BSD 3-Clause License
Classifier: Development Status :: 4 - Beta
Classifier: Environment :: Console
Classifier: Framework :: Django
Classifier: Intended Audience :: Developers
Classifier: License :: OSI Approved :: BSD License
Classifier: Programming Language :: Python
Classifier: Programming Language :: Python :: 3.8
Classifier: Programming Language :: Python :: 3.9
Classifier: Programming Language :: Python :: 3.10
Classifier: Programming Language :: Python :: 3.11
Classifier: Topic :: Software Development :: Testing
License-File: LICENSE.txt
Requires-Dist: django (<5.0,>=3.2)
Requires-Dist: selenium (<5.0,>=4.0)
